pyqflow/__init__.py
pyqflow/actor.py
pyqflow/asynchronous.py
pyqflow/constants.py
pyqflow/exceptions.py
pyqflow/functools.py
pyqflow/process.py
pyqflow/reader.py
pyqflow/remote.py
pyqflow/workflow.py
pyqflow-1.1.2.dist-info/METADATA
pyqflow-1.1.2.dist-info/WHEEL
pyqflow-1.1.2.dist-info/top_level.txt
pyqflow-1.1.2.dist-info/RECORD
