Metadata-Version: 2.1
Name: pyqflow
Version: 1.1.2
Summary: API for creating async workflows.
Home-page: https://github.com/dotmoovs/pyqflow
Author: Goncalo Faria, Guilherme Viveiros, Rui Reis.
Author-email: goncalo.faria@dotmoovs.com, guilherme.viveiros@dotmoovs.com, rui.reis@dotmoovs.com
Requires-Python: >=3.7.10
Requires-Dist: aiohttp-cors ==0.7.0
Requires-Dist: aioredis ==1.3.1
Requires-Dist: numpy >=1.19.5
Requires-Dist: ffmpeg-python
Requires-Dist: opencv-python
